<?xml version="1.0" encoding="UTF-8"?><wowhead><item id="174138"><name><![CDATA[Bracers of Dark Prophecy]]></name><level>595</level><quality id="4">Epic</quality><class id="4"><![CDATA[Armor]]></class><subclass id="2"><![CDATA[Leather Armor]]></subclass><icon displayId="181096">inv_bracer_leatherraidnzoth_d_01</icon><inventorySlot id="9">Wrist</inventorySlot><htmlTooltip><![CDATA[<table><tr><td><!--nstart--><b class="q4">Bracers of Dark Prophecy</b><!--nend--><!--ndstart--><br /><span><span style="color: #00FF00">Relinquished</span> <span style="color: #00FF00">Warforged</span> <span style="color: #00FF00">Titanforged</span></span><!--ndend--><span class="q"><br>Item Level <!--ilvl-->595</span><br /><!--bo-->Binds when picked up<table width="100%"><tr><td>Wrist</td><th><!--scstart4:2--><span class="q1">Leather</span><!--scend--></th></tr></table><span><!--amr-->741 Armor</span><br><span><!--stat73-->+1,307 [Agility or Intellect]</span><br><span><!--stat7-->+2,596 Stamina</span><!--ebstats--><br><span class="q2">+<!--rtg32-->150 Critical Strike</span><br><span class="q2">+<!--rtg36-->139 Haste</span><!--egstats--><!--eistats--><!--e--><!--ps--><br>Durability 55 / 55</td></tr></table><table><tr><td><!--itemEffects:0-->Requires Level <!--rlvl-->120<div class="whtt-sellprice">Sell Price: <span class="moneygold">39</span> <span class="moneysilver">21</span> <span class="moneycopper">86</span></div></td></tr></table>]]></htmlTooltip><json><![CDATA["appearances":{"0":[181096,""],"1":[181097,""],"3":[181100,"inv_bracer_leatherraidnzothmythic_d_01"],"4":[181099,""]},"armor":188,"bonustrees":[2748,2767,1522,1521,2819],"classs":4,"displayid":181096,"flags2":8192,"id":174138,"level":430,"name":"Bracers of Dark Prophecy","quality":4,"reqlevel":120,"slot":9,"slotbak":9,"source":[2],"sourcemore":[{"z":10522}],"specs":[270,105,261,269,102,260,268,259,103,104,577,581],"subclass":2]]></json><jsonEquip><![CDATA["agi":1307,"agiint":1307,"appearances":{"0":[181096,""],"1":[181097,""],"3":[181100,"inv_bracer_leatherraidnzothmythic_d_01"],"4":[181099,""]},"armor":741,"critstrkrtng":150,"displayid":181096,"dura":55,"hastertng":139,"int":1307,"reqlevel":120,"sellprice":392186,"slotbak":9,"sta":2596]]></jsonEquip><link>https://www.wowhead.com/item=174138</link></item></wowhead>