<?xml version="1.0" encoding="UTF-8"?><wowhead><item id="159614"><name><![CDATA[Galecaller's Boon]]></name><level>465</level><quality id="4">Epic</quality><class id="4"><![CDATA[Armor]]></class><subclass id="-4"><![CDATA[Trinkets]]></subclass><icon displayId="0">ability_shaman_fortifyingwaters</icon><inventorySlot id="12">Trinket</inventorySlot><htmlTooltip><![CDATA[<table><tr><td><!--nstart--><b class="q4">Galecaller's Boon</b><!--nend--><!--ndstart--><br /><span><span style="color: #00FF00">Relinquished</span> <span style="color: #00FF00">Warforged</span> <span style="color: #00FF00">Titanforged</span></span><!--ndend--><span class="q"><br>Item Level <!--ilvl-->465</span><br /><!--bo-->Binds when picked up<br />Unique-Equipped<table width="100%"><tr><td>Trinket</td><th><!--scstart4:-4--><span class="q1"></span><!--scend--></th></tr></table><span><!--stat3-->+658 Agility</span><!--ebstats--><!--egstats--><!--eistats--><!--e--><!--ps--></td></tr></table><table><tr><td><span class="q2">Use: <a href="https://www.wowhead.com/spell=268314" class="q2">Place a ward on the ground for 10 sec which increases your Haste by <!--pts1:0:0:268311:3.7561:crm-->1751<!----> and your Speed by <!--pts2:0:0:268311:3.7561:crm-->1751<!----> while you stand within it.</a> (1 Min Cooldown)</span><!--itemEffects:1--><br>Requires Level <!--rlvl-->120<div class="whtt-sellprice">Sell Price: <span class="moneygold">43</span> <span class="moneysilver">14</span> <span class="moneycopper">16</span></div></td></tr></table>]]></htmlTooltip><json><![CDATA["armor":0,"bonustrees":[1498,1492,1493,1497,2816],"classs":4,"flags2":8192,"id":159614,"level":300,"name":"Galecaller's Boon","quality":3,"reqlevel":120,"slot":12,"slotbak":12,"source":[2,5],"sourcemore":[{"z":9525},{"n":"Trinket Vendor","t":1,"ti":123107}],"specs":[260,268,261,254,269,259,103,104,253,577,255,263,581],"subclass":-4]]></json><jsonEquip><![CDATA["agi":658,"buyprice":2157082,"cooldown":60000,"reqlevel":120,"sellprice":431416,"slotbak":12]]></jsonEquip><link>https://www.wowhead.com/item=159614</link></item></wowhead>